README.md
setup.py
src/langbank/__init__.py
src/langbank/langbank.py
src/langbank/review_list.py
src/langbank.egg-info/PKG-INFO
src/langbank.egg-info/SOURCES.txt
src/langbank.egg-info/dependency_links.txt
src/langbank.egg-info/top_level.txt
tests/test.py