Metadata-Version: 2.1
Name: langbank
Version: 0.2.0
Summary: A simple word bank for language learning
Home-page: https://github.com/tebby24/langbank
Author: Teddy Gonyea
Author-email: enterted@gmail.com
Keywords: language learning
